Workbook

Sheet Summary
A1: HRMS Demo Test Tracker — Summary
A2: Live counts update from the "Test Cases" sheet. Edit only the yellow cells there.
A4: Suite | B4: Total | C4: Pass | D4: Fail | E4: Blocked | F4: Skipped | G4: Not run | H4: % Pass | I4: Done ✔
A5: Environment & test data | B5: =COUNTIF('Test Cases'!$B$2:$B$252,A5) | C5: =COUNTIFS('Test Cases'!$B$2:$B$252,$A5,'Test Cases'!$F$2:$F$252,"Pass") | D5: =COUNTIFS('Test Cases'!$B$2:$B$252,$A5,'Test Cases'!$F$2:$F$252,"Fail") | E5: =COUNTIFS('Test Cases'!$B$2:$B$252,$A5,'Test Cases'!$F$2:$F$252,"Blocked") | F5: =COUNTIFS('Test Cases'!$B$2:$B$252,$A5,'Test Cases'!$F$2:$F$252,"Skipped") | G5: =COUNTIFS('Test Cases'!$B$2:$B$252,$A5,'Test Cases'!$F$2:$F$252,"Not run") | H5: =IF(B5=0,0,C5/B5) | I5: =COUNTIFS('Test Cases'!$B$2:$B$252,$A5,'Test Cases'!$G$2:$G$252,TRUE)
A6: Landing & contact | B6: =COUNTIF('Test Cases'!$B$2:$B$252,A6) | C6: =COUNTIFS('Test Cases'!$B$2:$B$252,$A6,'Test Cases'!$F$2:$F$252,"Pass") | D6: =COUNTIFS('Test Cases'!$B$2:$B$252,$A6,'Test Cases'!$F$2:$F$252,"Fail") | E6: =COUNTIFS('Test Cases'!$B$2:$B$252,$A6,'Test Cases'!$F$2:$F$252,"Blocked") | F6: =COUNTIFS('Test Cases'!$B$2:$B$252,$A6,'Test Cases'!$F$2:$F$252,"Skipped") | G6: =COUNTIFS('Test Cases'!$B$2:$B$252,$A6,'Test Cases'!$F$2:$F$252,"Not run") | H6: =IF(B6=0,0,C6/B6) | I6: =COUNTIFS('Test Cases'!$B$2:$B$252,$A6,'Test Cases'!$G$2:$G$252,TRUE)
A7: Sign-in & session | B7: =COUNTIF('Test Cases'!$B$2:$B$252,A7) | C7: =COUNTIFS('Test Cases'!$B$2:$B$252,$A7,'Test Cases'!$F$2:$F$252,"Pass") | D7: =COUNTIFS('Test Cases'!$B$2:$B$252,$A7,'Test Cases'!$F$2:$F$252,"Fail") | E7: =COUNTIFS('Test Cases'!$B$2:$B$252,$A7,'Test Cases'!$F$2:$F$252,"Blocked") | F7: =COUNTIFS('Test Cases'!$B$2:$B$252,$A7,'Test Cases'!$F$2:$F$252,"Skipped") | G7: =COUNTIFS('Test Cases'!$B$2:$B$252,$A7,'Test Cases'!$F$2:$F$252,"Not run") | H7: =IF(B7=0,0,C7/B7) | I7: =COUNTIFS('Test Cases'!$B$2:$B$252,$A7,'Test Cases'!$G$2:$G$252,TRUE)
A8: Platform Admin console | B8: =COUNTIF('Test Cases'!$B$2:$B$252,A8) | C8: =COUNTIFS('Test Cases'!$B$2:$B$252,$A8,'Test Cases'!$F$2:$F$252,"Pass") | D8: =COUNTIFS('Test Cases'!$B$2:$B$252,$A8,'Test Cases'!$F$2:$F$252,"Fail") | E8: =COUNTIFS('Test Cases'!$B$2:$B$252,$A8,'Test Cases'!$F$2:$F$252,"Blocked") | F8: =COUNTIFS('Test Cases'!$B$2:$B$252,$A8,'Test Cases'!$F$2:$F$252,"Skipped") | G8: =COUNTIFS('Test Cases'!$B$2:$B$252,$A8,'Test Cases'!$F$2:$F$252,"Not run") | H8: =IF(B8=0,0,C8/B8) | I8: =COUNTIFS('Test Cases'!$B$2:$B$252,$A8,'Test Cases'!$G$2:$G$252,TRUE)
A9: Tenant config & wizard | B9: =COUNTIF('Test Cases'!$B$2:$B$252,A9) | C9: =COUNTIFS('Test Cases'!$B$2:$B$252,$A9,'Test Cases'!$F$2:$F$252,"Pass") | D9: =COUNTIFS('Test Cases'!$B$2:$B$252,$A9,'Test Cases'!$F$2:$F$252,"Fail") | E9: =COUNTIFS('Test Cases'!$B$2:$B$252,$A9,'Test Cases'!$F$2:$F$252,"Blocked") | F9: =COUNTIFS('Test Cases'!$B$2:$B$252,$A9,'Test Cases'!$F$2:$F$252,"Skipped") | G9: =COUNTIFS('Test Cases'!$B$2:$B$252,$A9,'Test Cases'!$F$2:$F$252,"Not run") | H9: =IF(B9=0,0,C9/B9) | I9: =COUNTIFS('Test Cases'!$B$2:$B$252,$A9,'Test Cases'!$G$2:$G$252,TRUE)
A10: Employee Master | B10: =COUNTIF('Test Cases'!$B$2:$B$252,A10) | C10: =COUNTIFS('Test Cases'!$B$2:$B$252,$A10,'Test Cases'!$F$2:$F$252,"Pass") | D10: =COUNTIFS('Test Cases'!$B$2:$B$252,$A10,'Test Cases'!$F$2:$F$252,"Fail") | E10: =COUNTIFS('Test Cases'!$B$2:$B$252,$A10,'Test Cases'!$F$2:$F$252,"Blocked") | F10: =COUNTIFS('Test Cases'!$B$2:$B$252,$A10,'Test Cases'!$F$2:$F$252,"Skipped") | G10: =COUNTIFS('Test Cases'!$B$2:$B$252,$A10,'Test Cases'!$F$2:$F$252,"Not run") | H10: =IF(B10=0,0,C10/B10) | I10: =COUNTIFS('Test Cases'!$B$2:$B$252,$A10,'Test Cases'!$G$2:$G$252,TRUE)
A11: Access management | B11: =COUNTIF('Test Cases'!$B$2:$B$252,A11) | C11: =COUNTIFS('Test Cases'!$B$2:$B$252,$A11,'Test Cases'!$F$2:$F$252,"Pass") | D11: =COUNTIFS('Test Cases'!$B$2:$B$252,$A11,'Test Cases'!$F$2:$F$252,"Fail") | E11: =COUNTIFS('Test Cases'!$B$2:$B$252,$A11,'Test Cases'!$F$2:$F$252,"Blocked") | F11: =COUNTIFS('Test Cases'!$B$2:$B$252,$A11,'Test Cases'!$F$2:$F$252,"Skipped") | G11: =COUNTIFS('Test Cases'!$B$2:$B$252,$A11,'Test Cases'!$F$2:$F$252,"Not run") | H11: =IF(B11=0,0,C11/B11) | I11: =COUNTIFS('Test Cases'!$B$2:$B$252,$A11,'Test Cases'!$G$2:$G$252,TRUE)
A12: Leave management | B12: =COUNTIF('Test Cases'!$B$2:$B$252,A12) | C12: =COUNTIFS('Test Cases'!$B$2:$B$252,$A12,'Test Cases'!$F$2:$F$252,"Pass") | D12: =COUNTIFS('Test Cases'!$B$2:$B$252,$A12,'Test Cases'!$F$2:$F$252,"Fail") | E12: =COUNTIFS('Test Cases'!$B$2:$B$252,$A12,'Test Cases'!$F$2:$F$252,"Blocked") | F12: =COUNTIFS('Test Cases'!$B$2:$B$252,$A12,'Test Cases'!$F$2:$F$252,"Skipped") | G12: =COUNTIFS('Test Cases'!$B$2:$B$252,$A12,'Test Cases'!$F$2:$F$252,"Not run") | H12: =IF(B12=0,0,C12/B12) | I12: =COUNTIFS('Test Cases'!$B$2:$B$252,$A12,'Test Cases'!$G$2:$G$252,TRUE)
A13: Attendance | B13: =COUNTIF('Test Cases'!$B$2:$B$252,A13) | C13: =COUNTIFS('Test Cases'!$B$2:$B$252,$A13,'Test Cases'!$F$2:$F$252,"Pass") | D13: =COUNTIFS('Test Cases'!$B$2:$B$252,$A13,'Test Cases'!$F$2:$F$252,"Fail") | E13: =COUNTIFS('Test Cases'!$B$2:$B$252,$A13,'Test Cases'!$F$2:$F$252,"Blocked") | F13: =COUNTIFS('Test Cases'!$B$2:$B$252,$A13,'Test Cases'!$F$2:$F$252,"Skipped") | G13: =COUNTIFS('Test Cases'!$B$2:$B$252,$A13,'Test Cases'!$F$2:$F$252,"Not run") | H13: =IF(B13=0,0,C13/B13) | I13: =COUNTIFS('Test Cases'!$B$2:$B$252,$A13,'Test Cases'!$G$2:$G$252,TRUE)
A14: Dashboard | B14: =COUNTIF('Test Cases'!$B$2:$B$252,A14) | C14: =COUNTIFS('Test Cases'!$B$2:$B$252,$A14,'Test Cases'!$F$2:$F$252,"Pass") | D14: =COUNTIFS('Test Cases'!$B$2:$B$252,$A14,'Test Cases'!$F$2:$F$252,"Fail") | E14: =COUNTIFS('Test Cases'!$B$2:$B$252,$A14,'Test Cases'!$F$2:$F$252,"Blocked") | F14: =COUNTIFS('Test Cases'!$B$2:$B$252,$A14,'Test Cases'!$F$2:$F$252,"Skipped") | G14: =COUNTIFS('Test Cases'!$B$2:$B$252,$A14,'Test Cases'!$F$2:$F$252,"Not run") | H14: =IF(B14=0,0,C14/B14) | I14: =COUNTIFS('Test Cases'!$B$2:$B$252,$A14,'Test Cases'!$G$2:$G$252,TRUE)
A15: Documents | B15: =COUNTIF('Test Cases'!$B$2:$B$252,A15) | C15: =COUNTIFS('Test Cases'!$B$2:$B$252,$A15,'Test Cases'!$F$2:$F$252,"Pass") | D15: =COUNTIFS('Test Cases'!$B$2:$B$252,$A15,'Test Cases'!$F$2:$F$252,"Fail") | E15: =COUNTIFS('Test Cases'!$B$2:$B$252,$A15,'Test Cases'!$F$2:$F$252,"Blocked") | F15: =COUNTIFS('Test Cases'!$B$2:$B$252,$A15,'Test Cases'!$F$2:$F$252,"Skipped") | G15: =COUNTIFS('Test Cases'!$B$2:$B$252,$A15,'Test Cases'!$F$2:$F$252,"Not run") | H15: =IF(B15=0,0,C15/B15) | I15: =COUNTIFS('Test Cases'!$B$2:$B$252,$A15,'Test Cases'!$G$2:$G$252,TRUE)
A16: Notifications | B16: =COUNTIF('Test Cases'!$B$2:$B$252,A16) | C16: =COUNTIFS('Test Cases'!$B$2:$B$252,$A16,'Test Cases'!$F$2:$F$252,"Pass") | D16: =COUNTIFS('Test Cases'!$B$2:$B$252,$A16,'Test Cases'!$F$2:$F$252,"Fail") | E16: =COUNTIFS('Test Cases'!$B$2:$B$252,$A16,'Test Cases'!$F$2:$F$252,"Blocked") | F16: =COUNTIFS('Test Cases'!$B$2:$B$252,$A16,'Test Cases'!$F$2:$F$252,"Skipped") | G16: =COUNTIFS('Test Cases'!$B$2:$B$252,$A16,'Test Cases'!$F$2:$F$252,"Not run") | H16: =IF(B16=0,0,C16/B16) | I16: =COUNTIFS('Test Cases'!$B$2:$B$252,$A16,'Test Cases'!$G$2:$G$252,TRUE)
... A22: Non-functional | B22: =COUNTIF('Test Cases'!$B$2:$B$252,A22) | C22: =COUNTIFS('Test Cases'!$B$2:$B$252,$A22,'Test Cases'!$F$2:$F$252,"Pass") | D22: =COUNTIFS('Test Cases'!$B$2:$B$252,$A22,'Test Cases'!$F$2:$F$252,"Fail") | E22: =COUNTIFS('Test Cases'!$B$2:$B$252,$A22,'Test Cases'!$F$2:$F$252,"Blocked") | F22: =COUNTIFS('Test Cases'!$B$2:$B$252,$A22,'Test Cases'!$F$2:$F$252,"Skipped") | G22: =COUNTIFS('Test Cases'!$B$2:$B$252,$A22,'Test Cases'!$F$2:$F$252,"Not run") | H22: =IF(B22=0,0,C22/B22) | I22: =COUNTIFS('Test Cases'!$B$2:$B$252,$A22,'Test Cases'!$G$2:$G$252,TRUE)
A23: TOTAL | B23: =SUM(B5:B22) | C23: =SUM(C5:C22) | D23: =SUM(D5:D22) | E23: =SUM(E5:E22) | F23: =SUM(F5:F22) | G23: =SUM(G5:G22) | H23: =IF(B23=0,0,C23/B23) | I23: =SUM(I5:I22)
A26: Overall readiness
A27: Total cases | B27: =B23
A28: Passed | B28: =C23
A29: Failed (open defects) | B29: =D23
A30: Not yet run | B30: =G23
A31: Demo ready? | B31: =IF(AND(D23=0,G23=0,B23>0),"YES — all cases passed",IF(COUNTIFS('Test Cases'!$B$2:$B$252,"ISO*")>0,IF(COUNTIFS('Test Cases'!$B$2:$B$252,"ISO*",'Test Cases'!$F$2:$F$252,"Fail")>0,"NO — tenant isolation failure (P0)","NOT YET — "&(D23+G23)&" open"),"NOT YET"))
A32: Isolation (ISO) failure is a P0 — stop the demo until fixed.

Sheet Test Cases
A1: Case ID | B1: Suite | C1: Section | D1: Test steps | E1: Expected result | F1: Status | G1: Done (✔) | H1: Tester | I1: Date tested | J1: Comments / observed behaviour | K1: Defect ID
A2: ENV-01 | B2: Environment & test data | C2: 2. Prerequisites & test data (complete BEFORE any suite) | D2: Open the **preview** web URL (Vercel) and the API health endpoint `GET /api/health` | E2: Web loads; health returns OK | F2: Not run | G2: FALSE
A3: ENV-02 | B3: Environment & test data | C3: 2. Prerequisites & test data (complete BEFORE any suite) | D3: Confirm you are on the **preview box**, not a laptop | E3: Background workers (email send, malware scan, accrual, attendance finalization, retention) run only on the preview box. On a laptop they are off and the Email log / scan states will not move | F3: Not run | G3: FALSE
A4: ENV-03 | B4: Environment & test data | C4: 2. Prerequisites & test data (complete BEFORE any suite) | D4: Confirm SES is configured (`SES_FROM_ADDRESS` + credentials) and the sender is verified | E4: Notification sends move to `SENT`. If unset, every send shows `FAILED — SES_FROM_ADDRESS is unset`. Fix before the demo or tell the client email is not live | F4: Not run | G4: FALSE
A5: ENV-04 | B5: Environment & test data | C5: 2. Prerequisites & test data (complete BEFORE any suite) | D5: Confirm ClamAV (`clamd`) is running on the preview box | E5: An EICAR test file is flagged (see DOC-10). Without clamd, uploads stay "pending scan" and cannot be downloaded (fail-closed — correct behaviour, but it looks broken) | F5: Not run | G5: FALSE
A6: ENV-05 | B6: Environment & test data | C6: 2. Prerequisites & test data (complete BEFORE any suite) | D6: Confirm Redis is up (BullMQ) | E6: Leave escalation and scheduled jobs can run | F6: Not run | G6: FALSE
A7: ENV-06 | B7: Environment & test data | C7: 2. Prerequisites & test data (complete BEFORE any suite) | D7: Confirm the platform operator account exists and can sign in to `/platform-admin` | E7: Operator console loads | F7: Not run | G7: FALSE
A8: ENV-07 | B8: Environment & test data | C8: 2. Prerequisites & test data (complete BEFORE any suite) | D8: Clear browser cache / use a private window per persona | E8: Avoids stale session tokens when switching personas | F8: Not run | G8: FALSE
A9: LAND-01 | B9: Landing & contact | C9: 3. Suite LAND — Public landing page & contact form | D9: Open the root URL signed out | E9: Public landing page renders; no dashboard; no sidebar | F9: Not run | G9: FALSE
A10: LAND-02 | B10: Landing & contact | C10: 3. Suite LAND — Public landing page & contact form | D10: Scroll to the `#contact` section; check layout on a phone-width viewport (≈390 px) | E10: Form is usable; no horizontal scrolling | F10: Not run | G10: FALSE
A11: LAND-03 | B11: Landing & contact | C11: 3. Suite LAND — Public landing page & contact form | D11: Submit the contact form with all required fields blank | E11: Client-side validation messages; nothing sent | F11: Not run | G11: FALSE
A12: LAND-04 | B12: Landing & contact | C12: 3. Suite LAND — Public landing page & contact form | D12: Submit a valid enquiry (name, company, work email, employee count, message) | E12: Success confirmation shown; a row is created (verify in PA-17 Leads) | F12: Not run | G12: FALSE
A13: LAND-05 | B13: Landing & contact | C13: 3. Suite LAND — Public landing page & contact form | D13: Submit 6+ times rapidly from the same client | E13: Rate limiter returns a friendly error after the limit; no crash | F13: Not run | G13: FALSE
... A252: NFR-08 | B252: Non-functional | C252: 19. Suite NFR — Non-functional | D252: `npm run build` and `npm run lint` at repo root | E252: Clean | F252: Not run | G252: FALSE

Sheet Defects
A1: Defect ID | B1: Case ID | C1: Severity | D1: Description (observed vs expected) | E1: Owner | F1: Status | G1: Fix / retest notes
A2: D-001
A3: D-002
A4: D-003
A5: D-004
A6: D-005
A7: D-006
A8: D-007
A9: D-008
A10: D-009
A11: D-010
A12: D-011
A13: D-012
... A41: D-040

Sheet How to use
A1: HOW TO USE THIS TRACKER
A3: 1. Test Cases sheet: one row per case. Work top to bottom (later suites depend on data from earlier ones).
A4: 2. Status (yellow dropdown): Not run / Pass / Fail / Blocked / Skipped.
A5: - Pass only if EVERY expected point holds. Partial = Fail.
A6: - Blocked = cannot run (say why in Comments). Skipped = deliberately not run (say why).
A7: 3. Done (✔): tick when the case is finished, whatever the outcome. Use the filter on Status to see what is left.
A8: 4. Tester and Date tested: who ran it and when.
A9: 5. Comments: write the observed behaviour, especially for Fail. Include screenshot names or request IDs if useful.
A10: 6. Defect ID: link a Fail to a row on the Defects sheet (D-001, D-002, …).
A11: 7. Summary sheet updates automatically. Do not type in it.
A13: Severity: P0 = tenant isolation or security (stop the demo). P1 = blocks a flow. P2 = wrong but has a workaround. P3 = cosmetic.
A14: Tip: filter the Test Cases sheet by Suite or Status to run one persona or area at a time.
A15: Tip: keep a copy per rehearsal (e.g. "Tracker - Rehearsal 1.xlsx") so you can compare runs.
